IbmDeveloperworksQuanbuJiaochengSanFix1/README.md
IbmDeveloperworksQuanbuJiaochengSanFix1/__init__.py
IbmDeveloperworksQuanbuJiaochengSanFix1/__main__.py
IbmDeveloperworksQuanbuJiaochengSanFix1/file.epub
IbmDeveloperworksQuanbuJiaochengSanFix1/index.html
IbmDeveloperworksQuanbuJiaochengSanFix1/css/__init__.py
IbmDeveloperworksQuanbuJiaochengSanFix1/css/annotations.css
IbmDeveloperworksQuanbuJiaochengSanFix1/css/main.css
IbmDeveloperworksQuanbuJiaochengSanFix1/css/normalize.css
IbmDeveloperworksQuanbuJiaochengSanFix1/css/popup.css
IbmDeveloperworksQuanbuJiaochengSanFix1/font/__init__.py
IbmDeveloperworksQuanbuJiaochengSanFix1/font/fontello.eot
IbmDeveloperworksQuanbuJiaochengSanFix1/font/fontello.svg
IbmDeveloperworksQuanbuJiaochengSanFix1/font/fontello.ttf
IbmDeveloperworksQuanbuJiaochengSanFix1/font/fontello.woff
IbmDeveloperworksQuanbuJiaochengSanFix1/img/__init__.py
IbmDeveloperworksQuanbuJiaochengSanFix1/img/annotator-glyph-sprite.png
IbmDeveloperworksQuanbuJiaochengSanFix1/img/annotator-icon-sprite.png
IbmDeveloperworksQuanbuJiaochengSanFix1/img/apple-touch-icon.png
IbmDeveloperworksQuanbuJiaochengSanFix1/img/cancelfullscreen.png
IbmDeveloperworksQuanbuJiaochengSanFix1/img/close.png
IbmDeveloperworksQuanbuJiaochengSanFix1/img/fullscreen.png
IbmDeveloperworksQuanbuJiaochengSanFix1/img/loader.gif
IbmDeveloperworksQuanbuJiaochengSanFix1/img/menu-icon.png
IbmDeveloperworksQuanbuJiaochengSanFix1/img/save.png
IbmDeveloperworksQuanbuJiaochengSanFix1/img/saved.png
IbmDeveloperworksQuanbuJiaochengSanFix1/img/settings-s.png
IbmDeveloperworksQuanbuJiaochengSanFix1/img/settings.png
IbmDeveloperworksQuanbuJiaochengSanFix1/img/star.png
IbmDeveloperworksQuanbuJiaochengSanFix1/js/__init__.py
IbmDeveloperworksQuanbuJiaochengSanFix1/js/epub.js
IbmDeveloperworksQuanbuJiaochengSanFix1/js/epub.min.js
IbmDeveloperworksQuanbuJiaochengSanFix1/js/epub.min.map
IbmDeveloperworksQuanbuJiaochengSanFix1/js/hooks.min.js
IbmDeveloperworksQuanbuJiaochengSanFix1/js/hooks.min.map
ibm_developerworks_quanbu_jiaocheng_san_fix1-2025.3.25.1.dist-info/METADATA
ibm_developerworks_quanbu_jiaocheng_san_fix1-2025.3.25.1.dist-info/WHEEL
ibm_developerworks_quanbu_jiaocheng_san_fix1-2025.3.25.1.dist-info/entry_points.txt
ibm_developerworks_quanbu_jiaocheng_san_fix1-2025.3.25.1.dist-info/top_level.txt
ibm_developerworks_quanbu_jiaocheng_san_fix1-2025.3.25.1.dist-info/RECORD
